examples/__init__.py
examples/bullying/__init__.py
examples/bullying/bullying_v1_data.py
examples/bullying/covid_data.py
examples/cascades/__init__.py
examples/cascades/test_cascades.py
examples/covid/__init__.py
examples/covid/covid.py
examples/covid/test_covid.py
skmixed/__init__.py
skmixed/helpers.py
skmixed/logger.py
skmixed/priors.py
skmixed/regularizers.py
skmixed/solvers.py
skmixed/legacy/__init__.py
skmixed/legacy/models.py
skmixed/legacy/oracles.py
skmixed/lme/__init__.py
skmixed/lme/cascades.py
skmixed/lme/models.py
skmixed/lme/oracles backup.py
skmixed/lme/oracles.py
skmixed/lme/problems.py
skmixed/lme/trees.py
tests/__init__.py
tests/test_core/__init__.py
tests/test_core/test_LinearLMEOracle.py
tests/test_core/test_LinearLMEOracleW.py
tests/test_core/test_LinearLMEProblem.py
tests/test_lasso/__init__.py
tests/test_lasso/test_LassoLMEModel.py
tests/test_lasso/test_LassoLMEModelFixedSelectivity.py
tests/test_sparse_models/__init__.py
tests/test_sparse_models/test_LinearLMESparseModel.py
tests/test_sparse_models/test_LinearLMESparseModel_with_selectiveness.py
tests/test_sparse_models/test_LmeModels.py
tests/test_trees/__init__.py
tests/test_trees/test_Forest.py
tests/test_trees/test_Tree.py
skmixed-0.1.2.dist-info/LICENSE
skmixed-0.1.2.dist-info/METADATA
skmixed-0.1.2.dist-info/WHEEL
skmixed-0.1.2.dist-info/top_level.txt
skmixed-0.1.2.dist-info/RECORD
