Metadata-Version: 2.1
Name: skmixed
Version: 0.1.2
Summary: UNKNOWN
Home-page: https://github.com/aksholokhov/skmixed
Author: Aleksei Sholokhov
Author-email: aksh@uw.edu
License: GPLv3+
Platform: UNKNOWN
Classifier: Programming Language :: Python :: 3
Classifier: License :: OSI Approved :: GNU General Public License v3 or later (GPLv3+)
Classifier: Operating System :: OS Independent
Requires-Python: >=3.6
Requires-Dist: numpy
Requires-Dist: scipy
Requires-Dist: sklearn
Requires-Dist: pytest
Requires-Dist: pandas
